{
  "ret": "0",
  "msg": "OK",
  "content": {
    "title": "abc",
    "type": "GET",
    "url": "/a/c",
    "allProject": [
      {
        "projectId": "0",
        "projectName": "百度众筹",
        "isActive": "1"
      },
      {
        "projectId": "1",
        "projectName": "信用卡开卡",
        "isActive": "0"
      },
      {
        "projectId": "2",
        "projectName": "信用卡权益",
        "isActive": "0"
      }
    ],
    "description": "将利用百度优秀的资源获得众筹资源，将利用百度优秀的资源获得众筹资源将利用百度优秀的资源获得众筹资源。1"
  }
}